ytmd_sdk/__init__.py
ytmd_sdk/events.py
ytmd_sdk/ytmd.py
ytmd_sdk/parser/__init__.py
ytmd_sdk/parser/converters.py
ytmd_sdk/parser/parser.py
ytmd_sdk/parser/player_state.py
ytmd_sdk/parser/queue.py
ytmd_sdk/parser/thumbnail.py
ytmd_sdk/parser/video_state.py
ytmd_sdk-1.0.1.dist-info/LICENSE
ytmd_sdk-1.0.1.dist-info/METADATA
ytmd_sdk-1.0.1.dist-info/WHEEL
ytmd_sdk-1.0.1.dist-info/top_level.txt
ytmd_sdk-1.0.1.dist-info/RECORD
