Metadata-Version: 2.1
Name: ytmd-sdk
Version: 1.0.1
Summary: A Python SDK for interacting with the YouTube Music Desktop App.
Maintainer-email: Damien Staeber <damienweifen@gmail.com>
Project-URL: Homepage, https://github.com/KillerBOSS2019/YTMD_SDK
Project-URL: Documentation, https://github.com/KillerBOSS2019/YTMD_SDK/blob/main/README.md
Project-URL: Repository, https://github.com/KillerBOSS2019/YTMD_SDK
Project-URL: Bug Tracker, https://github.com/KillerBOSS2019/YTMD_SDK/issues
Project-URL: Changelog, https://github.com/KillerBOSS2019/YTMD_SDK/blob/main/README.md#change-log
Keywords: youtube,music,desktop,sdk,api,ytmd,ytmd-sdk,youtube-music,youtube-music-desktop,youtube-music-desktop-app
Classifier: Development Status :: 5 - Production/Stable
Classifier: Intended Audience :: Developers
Classifier: Operating System :: Microsoft :: Windows :: Windows 10
Classifier: Operating System :: MacOS
Classifier: License :: OSI Approved :: GNU General Public License v3 or later (GPLv3+)
Classifier: Programming Language :: Python :: 3
Classifier: Programming Language :: Python :: 3.8
Classifier: Programming Language :: Python :: 3.9
Classifier: Programming Language :: Python :: 3.10
Requires-Python: >=3.8
License-File: LICENSE
Requires-Dist: requests ==2.31.0
Requires-Dist: websocket-client ==1.8.0
Requires-Dist: python-socketio ==5.11.2
